dmriphantomutils/__init__.py
dmriphantomutils/automask.py
dmriphantomutils/b_selection.py
dmriphantomutils/dipy_fit.py
dmriphantomutils/image_io.py
dmriphantomutils/scan_info.py
dmriphantomutils/transform_data.py
test/__init__.py
test/test_data.py
test/test_dipy_fit.py
test/test_image_io.py
test/test_scan_info.py
test/test_transform_data.py
dmriphantomutils-0.0.1.dist-info/LICENSE
dmriphantomutils-0.0.1.dist-info/METADATA
dmriphantomutils-0.0.1.dist-info/WHEEL
dmriphantomutils-0.0.1.dist-info/top_level.txt
dmriphantomutils-0.0.1.dist-info/RECORD
